{"text_length_sents": 2302, "text_length_clauses": 4347, "text_length_tokens": 34497, "reflective_passages_global": 543, "reflective_clauses": 1170, "reflective_tokens": 8359, "gi_passages_global": 272, "gi_clauses": 758, "gi_tokens": 5687, "nfr_passages_global": 84, "nfr_clauses": 210, "nfr_tokens": 1477, "comment_passages_global": 270, "comment_clauses": 714, "comment_tokens": 4884, "comment_nfr_passages_global": 25, "comment_nfr_clauses": 61, "comment_nfr_tokens": 421, "nfr_gi_passages_global": 40, "nfr_gi_clauses": 89, "nfr_gi_tokens": 644, "comment_gi_passages_global": 31, "comment_gi_clauses": 58, "comment_gi_tokens": 487, "comment_gi_nfr_passages_global": 13, "comment_gi_nfr_clauses": 25, "comment_gi_nfr_tokens": 200, "reflection_score_mean": 0.40046439412601015, "reflective_clauses_scored": 727.0, "reflective_clauses_new": 1170.0, "exception": "", "setting": ""}