{"nfr_clauses": [], "reflective_clauses": ["und wenn sie mich einsperren \u2013 ich nehme kein Wort zur\u00fcck", "M\u00f6gen sie mich zu 1000 Mark verurteilen", "und wir waren t\u00e4glich beisammen", "Man brauchte nur anzutippen, und alle Schleusen der Wut \u00f6ffneten sich gegen den armen Reinhold Ortmann", "So ein Schmierfink", "Hier gibt's keinen Vergleich", "da\u00df er ein unanst\u00e4ndiger Mensch ist", "Sie sind ein unanst\u00e4ndiger Mensch"], "gi_clauses": ["und wir waren t\u00e4glich beisammen", "Man brauchte nur anzutippen, und alle Schleusen der Wut \u00f6ffneten sich gegen den armen Reinhold Ortmann"], "comment_clauses": ["und wenn sie mich einsperren \u2013 ich nehme kein Wort zur\u00fcck", "M\u00f6gen sie mich zu 1000 Mark verurteilen", "So ein Schmierfink", "Hier gibt's keinen Vergleich", "da\u00df er ein unanst\u00e4ndiger Mensch ist", "Sie sind ein unanst\u00e4ndiger Mensch"], "gi_nfr_clauses": [], "comment_gi_clauses": [], "comment_nfr_clauses": [], "comment_gi_nfr_clauses": []}