{"text_length_sents": 2977, "text_length_clauses": 6240, "text_length_tokens": 52585, "reflective_passages_global": 281, "reflective_clauses": 704, "reflective_tokens": 5419, "gi_passages_global": 212, "gi_clauses": 614, "gi_tokens": 4816, "nfr_passages_global": 9, "nfr_clauses": 12, "nfr_tokens": 96, "comment_passages_global": 70, "comment_clauses": 104, "comment_tokens": 686, "comment_nfr_passages_global": 4, "comment_nfr_clauses": 5, "comment_nfr_tokens": 32, "nfr_gi_passages_global": 5, "nfr_gi_clauses": 7, "nfr_gi_tokens": 60, "comment_gi_passages_global": 3, "comment_gi_clauses": 3, "comment_gi_tokens": 20, "comment_gi_nfr_passages_global": 2, "comment_gi_nfr_clauses": 2, "comment_gi_nfr_tokens": 16, "reflection_score_mean": 0.34838782454105793, "reflective_clauses_scored": 110.0, "reflective_clauses_new": 704.0, "exception": "", "setting": ""}