{"text_length_sents": 179, "text_length_clauses": 272, "text_length_tokens": 1928, "reflective_passages_global": 17, "reflective_clauses": 38, "reflective_tokens": 347, "gi_passages_global": 11, "gi_clauses": 30, "gi_tokens": 289, "nfr_passages_global": 1, "nfr_clauses": 2, "nfr_tokens": 19, "comment_passages_global": 6, "comment_clauses": 8, "comment_tokens": 58, "comment_nfr_passages_global": 0, "comment_nfr_clauses": 0, "comment_nfr_tokens": 0, "nfr_gi_passages_global": 1, "nfr_gi_clauses": 2, "nfr_gi_tokens": 19, "comment_gi_passages_global": 0, "comment_gi_clauses": 0, "comment_gi_tokens": 0, "comment_gi_nfr_passages_global": 0, "comment_gi_nfr_clauses": 0, "comment_gi_nfr_tokens": 0, "reflection_score_mean": 0.3552076801682688, "reflective_clauses_scored": 10.0, "reflective_clauses_new": 38.0, "exception": "", "setting": ""}