{"text_length_sents": 2608, "text_length_clauses": 4296, "text_length_tokens": 33915, "reflective_passages_global": 599, "reflective_clauses": 1198, "reflective_tokens": 8411, "gi_passages_global": 259, "gi_clauses": 612, "gi_tokens": 4768, "nfr_passages_global": 75, "nfr_clauses": 179, "nfr_tokens": 1267, "comment_passages_global": 343, "comment_clauses": 813, "comment_tokens": 5188, "comment_nfr_passages_global": 25, "comment_nfr_clauses": 61, "comment_nfr_tokens": 430, "nfr_gi_passages_global": 41, "nfr_gi_clauses": 92, "nfr_gi_tokens": 668, "comment_gi_passages_global": 28, "comment_gi_clauses": 66, "comment_gi_tokens": 499, "comment_gi_nfr_passages_global": 16, "comment_gi_nfr_clauses": 42, "comment_gi_nfr_tokens": 306, "reflection_score_mean": 0.4046637137728962, "reflective_clauses_scored": 832.0, "reflective_clauses_new": 1198.0, "exception": "", "setting": ""}