{"text_length_sents": 4606, "text_length_clauses": 5596, "text_length_tokens": 32156, "reflective_passages_global": 653, "reflective_clauses": 1188, "reflective_tokens": 6546, "gi_passages_global": 282, "gi_clauses": 636, "gi_tokens": 3784, "nfr_passages_global": 135, "nfr_clauses": 284, "nfr_tokens": 1707, "comment_passages_global": 370, "comment_clauses": 859, "comment_tokens": 4599, "comment_nfr_passages_global": 42, "comment_nfr_clauses": 92, "comment_nfr_tokens": 513, "nfr_gi_passages_global": 70, "nfr_gi_clauses": 130, "nfr_gi_tokens": 824, "comment_gi_passages_global": 50, "comment_gi_clauses": 100, "comment_gi_tokens": 618, "comment_gi_nfr_passages_global": 28, "comment_gi_nfr_clauses": 57, "comment_gi_nfr_tokens": 346, "reflection_score_mean": 0.389048710422293, "reflective_clauses_scored": 907.0, "reflective_clauses_new": 1188.0, "exception": "", "setting": ""}